leadergpu/__init__.py
leadergpu/__version__.py
leadergpu/constants.py
leadergpu/exceptions.py
leadergpu/leadergpu.py
leadergpu/authentication/__init__.py
leadergpu/authentication/authentication.py
leadergpu/http_client/__init__.py
leadergpu/http_client/http_client.py
leadergpu/products/__init__.py
leadergpu/products/products.py
leadergpu/servers/__init__.py
leadergpu/servers/servers.py
leadergpu_python-0.1.3.dist-info/LICENSE
leadergpu_python-0.1.3.dist-info/METADATA
leadergpu_python-0.1.3.dist-info/WHEEL
leadergpu_python-0.1.3.dist-info/top_level.txt
leadergpu_python-0.1.3.dist-info/RECORD
