Metadata-Version: 2.1
Name: leadergpu-python
Version: 0.1.3
Summary: Python SDK for LeaderGPU Public API
Home-page: https://www.leadergpu.com/
Author: Marcus Edel
Author-email: marcus@urgs.org
Classifier: Programming Language :: Python :: 3
Classifier: Programming Language :: Python :: 3.6
Classifier: Programming Language :: Python :: 3.7
Classifier: Programming Language :: Python :: 3.8
Classifier: Programming Language :: Python :: 3.9
Classifier: Programming Language :: Python :: 3.10
Classifier: Programming Language :: Python :: 3.11
Classifier: Development Status :: 5 - Production/Stable
Classifier: Intended Audience :: Developers
Classifier: License :: OSI Approved :: MIT License
Classifier: Operating System :: OS Independent
Classifier: Natural Language :: English
Requires-Python: >=3.6
License-File: LICENSE
Requires-Dist: requests <3,>=2.25.1
Provides-Extra: dev
Provides-Extra: test
Requires-Dist: pytest <7,>=6.2.1 ; extra == 'test'
Requires-Dist: pytest-cov <3,>=2.10.1 ; extra == 'test'
Requires-Dist: pytest-responses <1,>=0.4.0 ; extra == 'test'
Requires-Dist: responses <1,>=0.12.1 ; extra == 'test'
